jupyterlab_highlight_selected_word/__init__.py
jupyterlab_highlight_selected_word/_version.py
jupyterlab_highlight_selected_word-0.1.1.data/data/share/jupyter/labextensions/jupyterlab-highlight-selected-word/package.json
jupyterlab_highlight_selected_word-0.1.1.data/data/share/jupyter/labextensions/jupyterlab-highlight-selected-word/schemas/jupyterlab-highlight-selected-word/package.json.orig
jupyterlab_highlight_selected_word-0.1.1.data/data/share/jupyter/labextensions/jupyterlab-highlight-selected-word/schemas/jupyterlab-highlight-selected-word/plugin.json
jupyterlab_highlight_selected_word-0.1.1.data/data/share/jupyter/labextensions/jupyterlab-highlight-selected-word/static/53.e1e24655c73c42b36ced.js
jupyterlab_highlight_selected_word-0.1.1.data/data/share/jupyter/labextensions/jupyterlab-highlight-selected-word/static/728.84a518a5bd74e8b2280d.js
jupyterlab_highlight_selected_word-0.1.1.data/data/share/jupyter/labextensions/jupyterlab-highlight-selected-word/static/remoteEntry.5b76d3ba64d58eed4ae5.js
jupyterlab_highlight_selected_word-0.1.1.data/data/share/jupyter/labextensions/jupyterlab-highlight-selected-word/static/style.js
jupyterlab_highlight_selected_word-0.1.1.data/data/share/jupyter/labextensions/jupyterlab-highlight-selected-word/static/third-party-licenses.json
jupyterlab_highlight_selected_word-0.1.1.data/data/share/jupyter/labextensions/jupyterlab-highlight-selected-word/install.json
jupyterlab_highlight_selected_word-0.1.1.dist-info/METADATA
jupyterlab_highlight_selected_word-0.1.1.dist-info/WHEEL
jupyterlab_highlight_selected_word-0.1.1.dist-info/licenses/LICENSE
jupyterlab_highlight_selected_word-0.1.1.dist-info/RECORD
