Metadata-Version: 2.4
Name: jupyterlab_highlight_selected_word
Version: 0.1.1
Summary: Highlight selected word in JupyterLab
Project-URL: Homepage, https://github.com/trort/jupyterlab_highlight_selected_word
Project-URL: Bug Tracker, https://github.com/trort/jupyterlab_highlight_selected_word/issues
Project-URL: Repository, https://github.com/trort/jupyterlab_highlight_selected_word.git
Author: Antigravity
License: BSD 3-Clause License
License-File: LICENSE
Keywords: jupyter,jupyterlab,jupyterlab-extension
Classifier: Framework :: Jupyter
Classifier: Framework :: Jupyter :: JupyterLab
Classifier: Framework :: Jupyter :: JupyterLab :: 4
Classifier: Framework :: Jupyter :: JupyterLab :: Extensions
Classifier: Framework :: Jupyter :: JupyterLab :: Extensions :: Prebuilt
Classifier: License :: OSI Approved :: BSD License
Classifier: Programming Language :: Python
Classifier: Programming Language :: Python :: 3
Classifier: Programming Language :: Python :: 3.10
Classifier: Programming Language :: Python :: 3.11
Classifier: Programming Language :: Python :: 3.12
Classifier: Programming Language :: Python :: 3.13
Classifier: Programming Language :: Python :: 3.14
Requires-Python: >=3.10
